kaleidoswap-0.4.0.dist-info/METADATA
kaleidoswap-0.4.0.dist-info/WHEEL
kaleidoswap/__init__.py
kaleidoswap/client.py
kaleidoswap/exceptions.py
kaleidoswap/generated_models.py
kaleidoswap/kaleidoswap.abi3.so
kaleidoswap/rgb_node_models.py
kaleidoswap/sub_clients.py
kaleidoswap-0.4.0.dist-info/RECORD
