Metadata-Version: 2.4
Name: kaleidoswap
Version: 0.4.0
Classifier: Development Status :: 4 - Beta
Classifier: Intended Audience :: Developers
Classifier: License :: OSI Approved :: MIT License
Classifier: Programming Language :: Python :: 3
Classifier: Programming Language :: Python :: 3.8
Classifier: Programming Language :: Python :: 3.9
Classifier: Programming Language :: Python :: 3.10
Classifier: Programming Language :: Python :: 3.11
Classifier: Programming Language :: Python :: 3.12
Classifier: Programming Language :: Rust
Classifier: Topic :: Software Development :: Libraries :: Python Modules
Requires-Dist: pydantic[email]>=2.10.6
Requires-Dist: pytest>=7.0 ; extra == 'dev'
Requires-Dist: pytest-asyncio>=0.21 ; extra == 'dev'
Requires-Dist: black>=23.0 ; extra == 'dev'
Requires-Dist: ruff>=0.1.0 ; extra == 'dev'
Requires-Dist: isort>=5.12 ; extra == 'dev'
Requires-Dist: datamodel-code-generator[http]>=0.27.3 ; extra == 'dev'
Provides-Extra: dev
Summary: Python SDK for the Kaleidoswap protocol - trade RGB assets on Lightning Network
Keywords: bitcoin,lightning,rgb,swap,trading,kaleidoswap
License: MIT
Requires-Python: >=3.8
Project-URL: Homepage, https://kaleidoswap.com
Project-URL: Repository, https://github.com/kaleidoswap/kaleido-sdk
Project-URL: Documentation, https://docs.kaleidoswap.com/python
